patchxl/__init__.py
patchxl/patchxl.py
patchxl/utils.py
patchxl-0.0.5.dist-info/METADATA
patchxl-0.0.5.dist-info/WHEEL
patchxl-0.0.5.dist-info/top_level.txt
patchxl-0.0.5.dist-info/RECORD
